maraco/__init__.py
maraco/config/__init__.py
maraco/config/settings.py
maraco/core/__init__.py
maraco/core/classifier.py
maraco/core/feature_extractor.py
maraco/core/model.py
maraco/core/preprocessor.py
maraco/models/__init__.py
maraco/training/__init__.py
maraco/training/train_model.py
maraco/training/validate_model.py
maraco/utils/__init__.py
maraco/utils/audio_utils.py
maraco/utils/noise_reduction.py
maraco/utils/validation.py
maraco_api-0.1.0.dist-info/licenses/LICENSE
maraco_api-0.1.0.dist-info/METADATA
maraco_api-0.1.0.dist-info/WHEEL
maraco_api-0.1.0.dist-info/entry_points.txt
maraco_api-0.1.0.dist-info/top_level.txt
maraco_api-0.1.0.dist-info/RECORD
